apc/__init__.py
apc/llm.py
apc/logging.py
apc/core/__init__.py
apc/core/checkpoint.py
apc/core/conductor.py
apc/core/health_monitor.py
apc/core/worker.py
apc/core/workflow.py
apc/helpers/__init__.py
apc/helpers/logging.py
apc/helpers/llms/__init__.py
apc/helpers/llms/anthropic.py
apc/helpers/llms/azure_openai.py
apc/helpers/llms/base.py
apc/helpers/llms/gemini.py
apc/messages/__init__.py
apc/transport/__init__.py
apc/transport/grpc.py
apc/transport/websocket.py
apc_protocol-0.1.17.dist-info/METADATA
apc_protocol-0.1.17.dist-info/WHEEL
apc_protocol-0.1.17.dist-info/entry_points.txt
apc_protocol-0.1.17.dist-info/licenses/LICENSE
apc_protocol-0.1.17.dist-info/RECORD
