Metadata-Version: 2.4
Name: apc-protocol
Version: 0.1.17
Summary: Agent Protocol Conductor - A production-ready protocol for decentralized AI agent orchestration
Project-URL: Homepage, https://github.com/deepfarkade/apc-protocol
Project-URL: Documentation, https://github.com/deepfarkade/apc-protocol/blob/main/docs/documentation.md
Project-URL: Repository, https://github.com/deepfarkade/apc-protocol
Project-URL: Bug Tracker, https://github.com/deepfarkade/apc-protocol/issues
Project-URL: Examples, https://github.com/deepfarkade/apc-protocol/tree/main/examples
Project-URL: Production Guide, https://github.com/deepfarkade/apc-protocol/blob/main/docs/PRODUCTION_GUIDE.md
Author-email: APC Contributors <contributors@apc-protocol.org>
Maintainer-email: APC Contributors <contributors@apc-protocol.org>
License: MIT License
License-File: LICENSE
Keywords: agent,ai,distributed,microservices,orchestration,protocol,workflow
Classifier: Development Status :: 4 - Beta
Classifier: Intended Audience :: Developers
Classifier: License :: OSI Approved :: MIT License
Classifier: Programming Language :: Python :: 3
Classifier: Programming Language :: Python :: 3.8
Classifier: Programming Language :: Python :: 3.9
Classifier: Programming Language :: Python :: 3.10
Classifier: Programming Language :: Python :: 3.11
Classifier: Programming Language :: Python :: 3.12
Classifier: Topic :: Scientific/Engineering :: Artificial Intelligence
Classifier: Topic :: Software Development :: Libraries :: Application Frameworks
Classifier: Topic :: System :: Distributed Computing
Requires-Python: >=3.8
Requires-Dist: boto3>=1.26.0
Requires-Dist: grpcio-tools>=1.50.0
Requires-Dist: grpcio>=1.50.0
Requires-Dist: protobuf>=4.21.0
Requires-Dist: pydantic>=2.0.0
Requires-Dist: redis>=4.0.0
Requires-Dist: structlog>=22.0.0
Requires-Dist: websockets>=10.0
Provides-Extra: dev
Requires-Dist: black>=22.0.0; extra == 'dev'
Requires-Dist: isort>=5.10.0; extra == 'dev'
Requires-Dist: mypy>=1.0.0; extra == 'dev'
Requires-Dist: pytest-asyncio>=0.21.0; extra == 'dev'
Requires-Dist: pytest>=7.0.0; extra == 'dev'
Requires-Dist: ruff>=0.1.0; extra == 'dev'
Provides-Extra: examples
Requires-Dist: anthropic>=0.3.0; extra == 'examples'
Requires-Dist: httpx>=0.24.0; extra == 'examples'
Requires-Dist: openai>=1.0.0; extra == 'examples'
